pygifconvt_moon/__init__.py
pygifconvt_moon/converter.py
pygifconvt_moon-1.0.1.dist-info/licenses/LICENSE
pygifconvt_moon-1.0.1.dist-info/METADATA
pygifconvt_moon-1.0.1.dist-info/WHEEL
pygifconvt_moon-1.0.1.dist-info/top_level.txt
pygifconvt_moon-1.0.1.dist-info/RECORD
