Metadata-Version: 2.4
Name: pygifconvt_moon
Version: 1.0.1
Summary: Test package for distribution
Home-page: 
Download-URL: 
Author: moonsookim
Author-email: moon4656@gmail.com
Keywords: GIFCONVERTER,pygifconvt_moon
Classifier: Programming Language :: Python :: 3
Classifier: License :: OSI Approved :: MIT License
Classifier: Operating System :: OS Independent
Requires-Python: >=3
License-File: LICENSE
Requires-Dist: pillow
Dynamic: author
Dynamic: author-email
Dynamic: classifier
Dynamic: keywords
Dynamic: license-file
Dynamic: requires-dist
Dynamic: requires-python
Dynamic: summary
